streamlit_searchbar/__init__.py
streamlit_searchbar/frontend/index.html
streamlit_searchbar/frontend/main.js
streamlit_searchbar/frontend/streamlit-component-lib.js
streamlit_searchbar/frontend/style.css
streamlit_searchbar-0.2.3.dist-info/LICENSE
streamlit_searchbar-0.2.3.dist-info/METADATA
streamlit_searchbar-0.2.3.dist-info/WHEEL
streamlit_searchbar-0.2.3.dist-info/top_level.txt
streamlit_searchbar-0.2.3.dist-info/RECORD
