Metadata-Version: 2.1
Name: streamlit-searchbar
Version: 0.2.3
Summary: Search bar component
Author: Anthony Alteirac
Author-email: anthony@alteirac.com
Requires-Python: >=3.7
License-File: LICENSE
